mo_logs/__init__.py
mo_logs/constants.py
mo_logs/convert.py
mo_logs/exceptions.py
mo_logs/log_usingEmail.py
mo_logs/log_usingFile.py
mo_logs/log_usingHandler.py
mo_logs/log_usingLogger.py
mo_logs/log_usingMozLog.py
mo_logs/log_usingMulti.py
mo_logs/log_usingNothing.py
mo_logs/log_usingPrint.py
mo_logs/log_usingSES.py
mo_logs/log_usingStream.py
mo_logs/log_usingThread.py
mo_logs/logger.py
mo_logs/startup.py
mo_logs/strings.py
mo_logs/utils.py
mo_logs-8.685.25166.dist-info/licenses/LICENSE
mo_logs-8.685.25166.dist-info/METADATA
mo_logs-8.685.25166.dist-info/WHEEL
mo_logs-8.685.25166.dist-info/top_level.txt
mo_logs-8.685.25166.dist-info/RECORD
